flytekit/__init__.py
flytekit/_version.py
flytekit/loggers.py
flytekit/_ast/__init__.py
flytekit/_ast/parser.py
flytekit/bin/__init__.py
flytekit/bin/entrypoint.py
flytekit/clients/__init__.py
flytekit/clients/auth_helper.py
flytekit/clients/friendly.py
flytekit/clients/helpers.py
flytekit/clients/raw.py
flytekit/clients/auth/__init__.py
flytekit/clients/auth/auth_client.py
flytekit/clients/auth/authenticator.py
flytekit/clients/auth/default_html.py
flytekit/clients/auth/exceptions.py
flytekit/clients/auth/keyring.py
flytekit/clients/auth/token_client.py
flytekit/clients/grpc_utils/__init__.py
flytekit/clients/grpc_utils/auth_interceptor.py
flytekit/clients/grpc_utils/default_metadata_interceptor.py
flytekit/clients/grpc_utils/wrap_exception_interceptor.py
flytekit/clis/__init__.py
flytekit/clis/helpers.py
flytekit/clis/version.py
flytekit/clis/flyte_cli/__init__.py
flytekit/clis/flyte_cli/example.config
flytekit/clis/flyte_cli/main.py
flytekit/clis/sdk_in_container/__init__.py
flytekit/clis/sdk_in_container/backfill.py
flytekit/clis/sdk_in_container/build.py
flytekit/clis/sdk_in_container/constants.py
flytekit/clis/sdk_in_container/executions.py
flytekit/clis/sdk_in_container/fetch.py
flytekit/clis/sdk_in_container/get.py
flytekit/clis/sdk_in_container/helpers.py
flytekit/clis/sdk_in_container/init.py
flytekit/clis/sdk_in_container/launchplan.py
flytekit/clis/sdk_in_container/local_cache.py
flytekit/clis/sdk_in_container/metrics.py
flytekit/clis/sdk_in_container/package.py
flytekit/clis/sdk_in_container/pyflyte.py
flytekit/clis/sdk_in_container/register.py
flytekit/clis/sdk_in_container/run.py
flytekit/clis/sdk_in_container/serialize.py
flytekit/clis/sdk_in_container/serve.py
flytekit/clis/sdk_in_container/utils.py
flytekit/configuration/__init__.py
flytekit/configuration/default_images.py
flytekit/configuration/feature_flags.py
flytekit/configuration/file.py
flytekit/configuration/internal.py
flytekit/configuration/plugin.py
flytekit/constants/__init__.py
flytekit-1.16.11.dist-info/licenses/LICENSE
flytekit-1.16.11.dist-info/METADATA
flytekit-1.16.11.dist-info/WHEEL
flytekit-1.16.11.dist-info/entry_points.txt
flytekit-1.16.11.dist-info/top_level.txt
flytekit-1.16.11.dist-info/RECORD
