Metadata-Version: 2.4
Name: flytekit
Version: 1.16.11
Summary: Flyte SDK for Python
Author-email: Flyte Contributors <admin@flyte.org>
License: Apache-2.0
Project-URL: Homepage, https://github.com/flyteorg/flytekit
Classifier: Intended Audience :: Science/Research
Classifier: Intended Audience :: Developers
Classifier: License :: OSI Approved :: Apache Software License
Classifier: Programming Language :: Python :: 3.9
Classifier: Programming Language :: Python :: 3.10
Classifier: Programming Language :: Python :: 3.11
Classifier: Programming Language :: Python :: 3.12
Classifier: Topic :: Scientific/Engineering
Classifier: Topic :: Scientific/Engineering :: Artificial Intelligence
Classifier: Topic :: Software Development
Classifier: Topic :: Software Development :: Libraries
Classifier: Topic :: Software Development :: Libraries :: Python Modules
Requires-Python: <3.13,>=3.9
License-File: LICENSE
Requires-Dist: adlfs>=2023.3.0
Requires-Dist: click>=6.6
Requires-Dist: cloudpickle>=2.0.0
Requires-Dist: croniter>=0.3.20
Requires-Dist: dataclasses-json<0.5.12,>=0.5.2
Requires-Dist: diskcache>=5.2.1
Requires-Dist: docker>=4.0.0
Requires-Dist: docstring-parser>=0.9.0
Requires-Dist: flyteidl<2.0.0a0,>=1.16.1
Requires-Dist: fsspec>=2023.3.0
Requires-Dist: gcsfs!=2024.2.0,!=2025.5.0,!=2025.5.0post1,>=2023.3.0
Requires-Dist: googleapis-common-protos>=1.57
Requires-Dist: grpcio
Requires-Dist: grpcio-status
Requires-Dist: importlib-metadata
Requires-Dist: joblib
Requires-Dist: jsonlines
Requires-Dist: jsonpickle
Requires-Dist: keyring>=18.0.1
Requires-Dist: markdown-it-py
Requires-Dist: marshmallow-enum
Requires-Dist: marshmallow-jsonschema>=0.12.0
Requires-Dist: mashumaro>=3.15
Requires-Dist: msgpack>=1.1.0
Requires-Dist: protobuf!=4.25.0
Requires-Dist: pygments
Requires-Dist: python-json-logger>=2.0.0
Requires-Dist: pytimeparse>=1.1.8
Requires-Dist: pyyaml!=5.4.0,!=5.4.1,!=6.0.0
Requires-Dist: requests>=2.18.4
Requires-Dist: rich
Requires-Dist: rich_click
Requires-Dist: s3fs!=2024.3.1,>=2023.3.0
Requires-Dist: statsd>=3.0.0
Requires-Dist: typing_extensions
Requires-Dist: urllib3>=1.22
Provides-Extra: agent
Requires-Dist: grpcio-health-checking<=1.68.0; extra == "agent"
Requires-Dist: httpx; extra == "agent"
Requires-Dist: prometheus-client; extra == "agent"
Provides-Extra: connector
Requires-Dist: grpcio-health-checking<=1.68.0; extra == "connector"
Requires-Dist: httpx; extra == "connector"
Requires-Dist: prometheus-client; extra == "connector"
Dynamic: license-file
